aiutil/__init__.py
aiutil/collections.py
aiutil/cv.py
aiutil/dataframe.py
aiutil/datetime.py
aiutil/dockerhub.py
aiutil/filesystem.py
aiutil/hash.py
aiutil/memory.py
aiutil/pdf.py
aiutil/pypi.py
aiutil/shebang.py
aiutil/shell.py
aiutil/sql.py
aiutil/url.py
aiutil/utils.py
aiutil/hadoop/__init__.py
aiutil/hadoop/hdfs.py
aiutil/hadoop/kerberos.py
aiutil/hadoop/log.py
aiutil/hadoop/logf.py
aiutil/hadoop/pyspark_submit.py
aiutil/hadoop/pyspark_submit.yaml
aiutil/notebook/__init__.py
aiutil/notebook/search.py
aiutil/notebook/util.py
aiutil-0.91.0.dist-info/METADATA
aiutil-0.91.0.dist-info/WHEEL
aiutil-0.91.0.dist-info/entry_points.txt
aiutil-0.91.0.dist-info/RECORD
