Metadata-Version: 2.4
Name: aiutil
Version: 0.91.0
Summary: A utils Python package for data scientists.
Project-URL: Repository, https://github.com/legendu-net/aiutil
Author-email: Benjamin Du <longendu@yahoo.com>
License-Expression: MIT
Keywords: AI,Machine Learning,tools,utils
Requires-Python: <4,>=3.10
Requires-Dist: dulwich>=0.20.24
Requires-Dist: loguru>=0.3.2
Requires-Dist: nbconvert>=7.16.6
Requires-Dist: nbformat>=5.10.4
Requires-Dist: notifiers>=1.2.1
Requires-Dist: numpy>=2.2.6
Requires-Dist: pandas>=1.2.0
Requires-Dist: python-magic>=0.4.0
Requires-Dist: pyyaml>=5.3.1
Requires-Dist: scikit-image>=0.18.3
Requires-Dist: sqlparse>=0.4.1
Requires-Dist: tqdm>=4.59.0
Provides-Extra: admin
Requires-Dist: psutil>=5.7.3; extra == 'admin'
Provides-Extra: all
Requires-Dist: nbconvert>=5.6.1; extra == 'all'
Requires-Dist: nbformat>=5.0.7; extra == 'all'
Requires-Dist: opencv-python>=4.0.0.0; extra == 'all'
Requires-Dist: pdfplumber>=0.11.7; extra == 'all'
Requires-Dist: pillow>=7.0.0; extra == 'all'
Requires-Dist: psutil>=5.7.3; extra == 'all'
Requires-Dist: pypdf>=3.16.1; extra == 'all'
Requires-Dist: requests>=2.20.0; extra == 'all'
Provides-Extra: cv
Requires-Dist: opencv-python>=4.0.0.0; extra == 'cv'
Requires-Dist: pillow>=7.0.0; extra == 'cv'
Provides-Extra: jupyter
Requires-Dist: nbconvert>=5.6.1; extra == 'jupyter'
Requires-Dist: nbformat>=5.0.7; extra == 'jupyter'
Provides-Extra: pdf
Requires-Dist: pdfplumber>=0.11.7; extra == 'pdf'
Requires-Dist: pypdf>=3.16.1; extra == 'pdf'
